pylayer.py
pylayer-1.0.0.dist-info/WHEEL
pylayer-1.0.0.dist-info/METADATA
pylayer-1.0.0.dist-info/RECORD
