Metadata-Version: 2.1
Name: pylayer
Version: 1.0.0
Summary: Make a end-to-end encryption pass. PASSWORD FROM MODULE: ePBfRsT23Le7C4DbM1WoIoo7PUr6VhuFqTOp
License: Grub BN - V3
Author: OwoNicoo
Requires-Python: >=3.9,<4.0
Classifier: License :: Other/Proprietary License
Classifier: Programming Language :: Python :: 3
Classifier: Programming Language :: Python :: 3.10
Classifier: Programming Language :: Python :: 3.9
